rubis/__init__.py
rubis/__main__.py
rubis/cli.py
rubis/core.py
rubis/hash.py
rubis/data/CN1_SM1_config.json
rubis/data/cygnus
rubis/data/default
rubis/data/default_config.json
rubis/data/mysql
rubis/data/one_board
rubis/data/raw
rubis-1.0.1.dist-info/LICENSE
rubis-1.0.1.dist-info/METADATA
rubis-1.0.1.dist-info/WHEEL
rubis-1.0.1.dist-info/entry_points.txt
rubis-1.0.1.dist-info/top_level.txt
rubis-1.0.1.dist-info/RECORD
