Metadata-Version: 2.1
Name: rubis
Version: 1.0.1
Summary: Control tool of ADC monitor board, "rubis" on Raspberry Pi
Home-page: https://github.com/mzks/rubis
Author: Keita Mizukoshi
Author-email: mzks@stu.kobe-u.ac.jp
Maintainer: Keita Mizukoshi
Maintainer-email: mzks@stu.kobe-u.ac.jp
License: MIT
Platform: UNKNOWN
Classifier: Programming Language :: Python :: 3
Classifier: License :: OSI Approved :: MIT License
License-File: LICENSE
Requires-Dist: PyMySQL
Requires-Dist: adafruit-circuitpython-ads1x15
Requires-Dist: psutil
